<?xml version="1.0"?>
<document xmlns="http://www.math.cuhk.edu.hk/~pschan/cranach">
  <course environment="" chapter_type="" type="Course" wbtag="course" title="Math 1030">
    <keywords slide="all" environ="course" chapter="" course="Math 1030">
      <keyword chapter="" slide="all">consistent</keyword>
      <keyword chapter="" slide="all">inconsistent</keyword>
      <keyword chapter="" slide="all">rank</keyword>
      <keyword chapter="" slide="all">free</keyword>
      <keyword chapter="" slide="all">independent</keyword>
      <keyword chapter="" slide="all">dependent</keyword>
      <keyword chapter="" slide="all">dependent</keyword>
      <keyword chapter="" slide="all">dependent variable</keyword>
      <keyword chapter="" slide="all">independent variable</keyword>
      <keyword chapter="" slide="all">free variable</keyword>
      <keyword chapter="" slide="all">Free and dependent variables</keyword>
      <keyword chapter="" slide="all">inconsistent</keyword>
      <keyword chapter="" slide="all">consistent</keyword>
      <keyword chapter="" slide="all">consistent</keyword>
      <keyword chapter="" slide="all">non-zero row</keyword>
      <keyword chapter="" slide="all">Steps of Solving a System of Linear Equations.</keyword>
      <keyword chapter="" slide="all">Independent and Dependent Variables</keyword>
      <keyword chapter="" slide="all">Recognizing Consistency of a Linear System</keyword>
      <keyword chapter="" slide="all">Consistent Systems r and n</keyword>
      <keyword chapter="" slide="all">Free Variables for Consistent Systems</keyword>
      <keyword chapter="" slide="all">Possible Solution Sets for Linear Systems</keyword>
      <keyword chapter="" slide="all">Consistent More Variables than Equations Infinite solutions</keyword>
    </keywords>
    <title environment="title" chapter_type="" wbtag="course" scope="course" course="Math 1030" chapter="" section="" subsection="" subsubsection="" serial="" slide="">Math 1030</title>
    <slides environment="" chapter_type="">
      <slide environment="" chapter_type="" canon_num="1" scope="course" course="Math 1030" title="Math 1030" id="s1" slide="1" chapter="" section="" subsection="" subsubsection="" chapter_title="" section_title="">
        <title environment="title" chapter_type="" wbtag="course" scope="course" course="" chapter="" section="" subsection="" subsubsection="" serial="" slide="1">Math 1030</title>
        <keywords slide="1" environ="slide" chapter="" course="Math 1030"/>
        <setchapter course="Math 1030" chapter="" chapter_type="" section="" subsection="" subsubsection="" environment="" wbtag="setchapter" argument="7"/>
      </slide>
    </slides>
    <chapter environment="" chapter_type="Chapter" type="Chapter" wbtag="chapter" num="7" title="Types of Solution Sets" course="Math 1030" serial="7">
      <keywords slide="all" environ="chapter" chapter="7" course="Math 1030">
        <keyword chapter="7" slide="all">consistent</keyword>
        <keyword chapter="7" slide="all">inconsistent</keyword>
        <keyword chapter="7" slide="all">rank</keyword>
        <keyword chapter="7" slide="all">free</keyword>
        <keyword chapter="7" slide="all">independent</keyword>
        <keyword chapter="7" slide="all">dependent</keyword>
        <keyword chapter="7" slide="all">dependent</keyword>
        <keyword chapter="7" slide="all">dependent variable</keyword>
        <keyword chapter="7" slide="all">independent variable</keyword>
        <keyword chapter="7" slide="all">free variable</keyword>
        <keyword chapter="7" slide="all">Free and dependent variables</keyword>
        <keyword chapter="7" slide="all">inconsistent</keyword>
        <keyword chapter="7" slide="all">consistent</keyword>
        <keyword chapter="7" slide="all">consistent</keyword>
        <keyword chapter="7" slide="all">non-zero row</keyword>
        <keyword chapter="7" slide="all">Steps of Solving a System of Linear Equations.</keyword>
        <keyword chapter="7" slide="all">Independent and Dependent Variables</keyword>
        <keyword chapter="7" slide="all">Recognizing Consistency of a Linear System</keyword>
        <keyword chapter="7" slide="all">Consistent Systems r and n</keyword>
        <keyword chapter="7" slide="all">Free Variables for Consistent Systems</keyword>
        <keyword chapter="7" slide="all">Possible Solution Sets for Linear Systems</keyword>
        <keyword chapter="7" slide="all">Consistent More Variables than Equations Infinite solutions</keyword>
      </keywords>
      <title environment="title" chapter_type="Chapter" wbtag="chapter" scope="chapter" course="Math 1030" chapter="7" section="" subsection="" subsubsection="" serial="7" slide="">Types of Solution Sets</title>
      <slides environment="" chapter_type="">
        <slide environment="" chapter_type="Chapter" canon_num="2" scope="chapter" id="s2" slide="2" course="Math 1030" chapter="7" section="" subsection="" subsubsection="" chapter_title="Types of Solution Sets" section_title="">
          <title environment="title" chapter_type="Chapter" wbtag="chapter" scope="chapter" course="" chapter="" section="" subsection="" subsubsection="" serial="" slide="2">Types of Solution Sets</title>
          <keywords slide="2" environ="slide" chapter="7" course="Math 1030"/>
          <newline course="Math 1030" chapter="7" chapter_type="" section="" subsection="" subsubsection="" environment=""/>
          <h5 xmlns="http://www.w3.org/1999/xhtml" class="notkw" environment="">
            <paragraphs xmlns="http://www.math.cuhk.edu.hk/~pschan/cranach" course="Math 1030" chapter="7" chapter_type="" section="" subsection="" subsubsection="" environment="" wbtag="paragraphs">Reference.</paragraphs>
          </h5>
          <paragraphs course="Math 1030" chapter="7" chapter_type="" section="" subsection="" subsubsection="" environment="" wbtag="paragraphs"> Beezer, Ver 3.5 Subsection TTS (print version p35 - p41)</paragraphs>
          <newline course="Math 1030" chapter="7" chapter_type="" section="" subsection="" subsubsection="" environment=""/>
          <h5 xmlns="http://www.w3.org/1999/xhtml" class="notkw" environment="">
            <paragraphs xmlns="http://www.math.cuhk.edu.hk/~pschan/cranach" course="Math 1030" chapter="7" chapter_type="" section="" subsection="" subsubsection="" environment="" wbtag="paragraphs">Exercise.</paragraphs>
          </h5>
          <paragraphs course="Math 1030" chapter="7" chapter_type="" section="" subsection="" subsubsection="" environment="" wbtag="paragraphs"> Exercises with solutions can be downloaded at http://linear.ups.edu/download/fcla-3.50-solution-manual.pdf
Section TSS (p.13 - 18) C21-28, T11, T20, T40, T41. </paragraphs>
        </slide>
      </slides>
      <section environment="" chapter_type="" type="Section" wbtag="section" title="Introduction" course="Math 1030" chapter="7" num="1" serial="7.1">
        <title environment="title" chapter_type="Chapter" wbtag="title" scope="section" course="Math 1030" chapter="7" section="1" subsection="" subsubsection="" serial="7.1" slide="">
          <paragraphs course="Math 1030" chapter="7" chapter_type="" section="1" subsection="" subsubsection="" environment="title" wbtag="paragraphs">Introduction</paragraphs>
        </title>
        <slides environment="" chapter_type="">
          <slide environment="" chapter_type="Chapter" canon_num="3" scope="section" id="s3" slide="3" course="Math 1030" chapter="7" section="1" subsection="" subsubsection="" chapter_title="Types of Solution Sets" section_title="Introduction">
            <keywords slide="3" environ="slide" chapter="7" course="Math 1030"/>
            <title environment="title" chapter_type="Chapter" wbtag="title" scope="section" course="Math 1030" chapter="7" section="1" subsection="" subsubsection="" serial="" slide="3">
              <paragraphs course="Math 1030" chapter="7" chapter_type="" section="1" subsection="" subsubsection="" environment="title" wbtag="paragraphs">Introduction</paragraphs>
            </title>
            <paragraphs course="Math 1030" chapter="7" chapter_type="" section="1" subsection="" subsubsection="" environment="" wbtag="paragraphs"> We will now be more careful about analyzing the reduced row-echelon form derived from the augmented matrix of a system of linear equations.
In particular, we will see how to systematically handle the situation when we have infinitely many solutions to a system, and we will prove that every system of linear equations has either zero, one or infinitely many solutions.
With these tools, we will be able to routinely solve any linear system. </paragraphs>
          </slide>
        </slides>
      </section>
      <section environment="" chapter_type="" type="Section" wbtag="section" title="Consistent Systems" course="Math 1030" chapter="7" num="2" serial="7.2">
        <title environment="title" chapter_type="Chapter" wbtag="title" scope="section" course="Math 1030" chapter="7" section="2" subsection="" subsubsection="" serial="7.2" slide="">
          <paragraphs course="Math 1030" chapter="7" chapter_type="" section="2" subsection="" subsubsection="" environment="title" wbtag="paragraphs">Consistent Systems</paragraphs>
        </title>
        <label wbtag="label" name="CS" type="Section"/>
        <slides environment="" chapter_type="">
          <slide environment="" chapter_type="Chapter" canon_num="4" scope="section" id="s4" slide="4" course="Math 1030" chapter="7" section="2" subsection="" subsubsection="" chapter_title="Types of Solution Sets" section_title="Consistent Systems">
            <keywords slide="4" environ="slide" chapter="7" course="Math 1030">
              <keyword chapter="7" slide="4">consistent</keyword>
              <keyword chapter="7" slide="4">inconsistent</keyword>
              <keyword chapter="7" slide="4">rank</keyword>
            </keywords>
            <title environment="title" chapter_type="Chapter" wbtag="title" scope="section" course="Math 1030" chapter="7" section="2" subsection="" subsubsection="" serial="" slide="4">
              <paragraphs course="Math 1030" chapter="7" chapter_type="" section="2" subsection="" subsubsection="" environment="title" wbtag="paragraphs">Consistent Systems</paragraphs>
            </title>
            <paragraphs course="Math 1030" chapter="7" chapter_type="" section="2" subsection="" subsubsection="" environment="" wbtag="paragraphs"> A system of linear equations is </paragraphs>
            <inline_keyword course="Math 1030" chapter="7" chapter_type="" section="2" subsection="" subsubsection="" environment="">consistent</inline_keyword>
            <paragraphs course="Math 1030" chapter="7" chapter_type="" section="2" subsection="" subsubsection="" environment="" wbtag="paragraphs"> if it has at least one solution. Otherwise, the system is called </paragraphs>
            <inline_keyword course="Math 1030" chapter="7" chapter_type="" section="2" subsection="" subsubsection="" environment="">inconsistent</inline_keyword>
            <paragraphs course="Math 1030" chapter="7" chapter_type="" section="2" subsection="" subsubsection="" environment="" wbtag="paragraphs">. </paragraphs>
            <statement environment="statement" chapter_type="Chapter" type="Example" wbtag="eg" num="1" md5="d916916307f8dd20dc5a87b211ab8512" course="Math 1030" chapter="7" slide="4" item="7.1">
              <newcol course="Math 1030" chapter="7" chapter_type="" section="2" subsection="" subsubsection="" environment="newcol" wbtag="newcol">
                <enumerate course="Math 1030" chapter="7" chapter_type="" section="2" subsection="" subsubsection="" environment="enumerate" wbtag="enumerate">
                  <item course="Math 1030" chapter="7" chapter_type="" section="2" subsection="" subsubsection="" environment="enumerate" wbtag="item">
                    <paragraphs course="Math 1030" chapter="7" chapter_type="" section="2" subsection="" subsubsection="" environment="enumerate" wbtag="paragraphs"> The system of linear equations
\begin{align*}
2x_1 + 3x_2 &amp;= 3 \\
x_1 - x_2 &amp;= 4
\end{align*}
is consistent because it has solution $(x_{1},x_{2})=(1,-3)$. </paragraphs>
                  </item>
                  <item course="Math 1030" chapter="7" chapter_type="" section="2" subsection="" subsubsection="" environment="enumerate" wbtag="item">
                    <paragraphs course="Math 1030" chapter="7" chapter_type="" section="2" subsection="" subsubsection="" environment="enumerate" wbtag="paragraphs"> The system of linear equations
\begin{align*}
2x_1+3x_2&amp;=3\\
4x_1+6x_2&amp;=6
\end{align*}
is consistent because has infinite many solutions: $\{(t,\frac{3-2t}{3})\,|\,t\text{ real number}\}$. </paragraphs>
                  </item>
                  <item course="Math 1030" chapter="7" chapter_type="" section="2" subsection="" subsubsection="" environment="enumerate" wbtag="item">
                    <paragraphs course="Math 1030" chapter="7" chapter_type="" section="2" subsection="" subsubsection="" environment="enumerate" wbtag="paragraphs"> The system of linear equations
\begin{align*}
2x_1+3x_2&amp;=3\\
4x_1+6x_2&amp;=10
\end{align*}
is inconsistent because it has no solution. </paragraphs>
                  </item>
                </enumerate>
              </newcol>
            </statement>
            <strong xmlns="http://www.w3.org/1999/xhtml" environment="">
              <paragraphs xmlns="http://www.math.cuhk.edu.hk/~pschan/cranach" course="Math 1030" chapter="7" chapter_type="" section="2" subsection="" subsubsection="" environment="" wbtag="paragraphs">Notation Recall</paragraphs>
            </strong>
            <paragraphs course="Math 1030" chapter="7" chapter_type="" section="2" subsection="" subsubsection="" environment="" wbtag="paragraphs">: </paragraphs>
            <newcol course="Math 1030" chapter="7" chapter_type="" section="2" subsection="" subsubsection="" environment="newcol" wbtag="newcol">
              <paragraphs course="Math 1030" chapter="7" chapter_type="" section="2" subsection="" subsubsection="" environment="newcol" wbtag="paragraphs"> Let $A$ be a reduced row echelon form. </paragraphs>
              <enumerate course="Math 1030" chapter="7" chapter_type="" section="2" subsection="" subsubsection="" environment="enumerate" wbtag="enumerate">
                <item course="Math 1030" chapter="7" chapter_type="" section="2" subsection="" subsubsection="" environment="enumerate" wbtag="item">
                  <paragraphs course="Math 1030" chapter="7" chapter_type="" section="2" subsection="" subsubsection="" environment="enumerate" wbtag="paragraphs"> The number of non-zero rows is called the </paragraphs>
                  <inline_keyword course="Math 1030" chapter="7" chapter_type="" section="2" subsection="" subsubsection="" environment="enumerate">rank</inline_keyword>
                  <paragraphs course="Math 1030" chapter="7" chapter_type="" section="2" subsection="" subsubsection="" environment="enumerate" wbtag="paragraphs"> of $A$ and is denoted by $r$. </paragraphs>
                </item>
                <item course="Math 1030" chapter="7" chapter_type="" section="2" subsection="" subsubsection="" environment="enumerate" wbtag="item">
                  <paragraphs course="Math 1030" chapter="7" chapter_type="" section="2" subsection="" subsubsection="" environment="enumerate" wbtag="paragraphs"> The set of the column indexes for the pivot columns is denoted by
\[D=\{(d_{1},d_{2},d_{3},\ldots,d_{r})\,|\,d_{1} &lt; d_{2} &lt; d_{3} &lt; \cdots &lt; d_{r}.\}\] </paragraphs>
                </item>
                <item course="Math 1030" chapter="7" chapter_type="" section="2" subsection="" subsubsection="" environment="enumerate" wbtag="item">
                  <paragraphs course="Math 1030" chapter="7" chapter_type="" section="2" subsection="" subsubsection="" environment="enumerate" wbtag="paragraphs"> The set of column indexes that are not pivot columns is denoted by
\[F=\{(f_{1},f_{2},f_{3},\ldots,f_{n-r})\,|\,f_{1} &lt; f_{2} &lt; f_{3}&lt; \cdots &lt; f_{n-r}.\}\] </paragraphs>
                </item>
              </enumerate>
            </newcol>
          </slide>
          <slide environment="" chapter_type="Chapter" wbtag="slide" canon_num="5" id="s5" slide="5" course="Math 1030" chapter="7" section="2" subsection="" subsubsection="" chapter_title="Types of Solution Sets" section_title="Consistent Systems">
            <keywords slide="5" environ="slide" chapter="7" course="Math 1030"/>
            <statement environment="statement" chapter_type="Chapter" type="Example" wbtag="eg" num="2" md5="3a9bb7f74b047d58d1230b6b956b4c2d" course="Math 1030" chapter="7" slide="5" item="7.2">
              <label wbtag="label" name="RREFN" type="Example"/>
              <paragraphs course="Math 1030" chapter="7" chapter_type="" section="2" subsection="" subsubsection="" environment="statement" wbtag="paragraphs"> Reduced row-echelon form notation
For the $5\times 9$ matrix
\[\displaystyle B=\begin{bmatrix}\boxed{1}&amp;5&amp;0&amp;0&amp;2&amp;8&amp;0&amp;5&amp;-1\\
0&amp;0&amp;\boxed{1}&amp;0&amp;4&amp;7&amp;0&amp;2&amp;0\\
0&amp;0&amp;0&amp;\boxed{1}&amp;3&amp;9&amp;0&amp;3&amp;-6\\
0&amp;0&amp;0&amp;0&amp;0&amp;0&amp;\boxed{1}&amp;4&amp;2\\
0&amp;0&amp;0&amp;0&amp;0&amp;0&amp;0&amp;0&amp;0\end{bmatrix}\]
in reduced row-echelon form we have:</paragraphs>
              <newline course="Math 1030" chapter="7" chapter_type="" section="2" subsection="" subsubsection="" environment="statement"/>
              <newcol course="Math 1030" chapter="7" chapter_type="" section="2" subsection="" subsubsection="" environment="newcol" wbtag="newcol">
                <paragraphs course="Math 1030" chapter="7" chapter_type="" section="2" subsection="" subsubsection="" environment="newcol" wbtag="paragraphs"> \begin{align*}
r&amp;=4\\
d_1&amp;=1
&amp;
d_2&amp;=3
&amp;
d_3&amp;=4
&amp;
d_4&amp;=7\\
f_1&amp;=2
&amp;
f_2&amp;=5
&amp;
f_3&amp;=6
&amp;
f_4&amp;=8
&amp;
f_5&amp;=9
\end{align*} </paragraphs>
                <collapse course="Math 1030" chapter="7" chapter_type="" section="2" subsection="" subsubsection="" environment="newcol" wbtag="collapse">
                  <paragraphs course="Math 1030" chapter="7" chapter_type="" section="2" subsection="" subsubsection="" environment="newcol" wbtag="paragraphs"> Notice that the sets
\[\displaystyle D=\{d_{1},\,d_{2},\,d_{3},\,d_{4}\}=\{1,\,3,\,4,\,7\}\]
have nothing in common and together account for all of the columns of $B$. </paragraphs>
                </collapse>
              </newcol>
            </statement>
          </slide>
          <slide environment="" chapter_type="Chapter" wbtag="slide" canon_num="6" id="s6" slide="6" course="Math 1030" chapter="7" section="2" subsection="" subsubsection="" chapter_title="Types of Solution Sets" section_title="Consistent Systems">
            <keywords slide="6" environ="slide" chapter="7" course="Math 1030">
              <keyword chapter="7" slide="6">free</keyword>
              <keyword chapter="7" slide="6">independent</keyword>
              <keyword chapter="7" slide="6">dependent</keyword>
              <keyword chapter="7" slide="6">dependent</keyword>
            </keywords>
            <statement environment="statement" chapter_type="Chapter" type="Example" wbtag="eg" num="3" md5="c9c216d455f4dff5f6142ce5cb2fc66b" course="Math 1030" chapter="7" slide="6" item="7.3">
              <label wbtag="label" name="ISSI" type="Example"/>
              <paragraphs course="Math 1030" chapter="7" chapter_type="" section="2" subsection="" subsubsection="" environment="statement" wbtag="paragraphs"> Describe the infinite solution set of the following system of linear equations
with $m=4$ equations in $n=7$ variables.
\begin{align*}
x_1 +4x_2  - x_4  + 7x_6 - 9x_7 &amp;= 3\\
2x_1 + 8x_2 - x_3 + 3x_4 + 9x_5 - 13x_6 + 7x_7 &amp;= 9\\
2x_3 -3x_4 -4x_5 +12x_6 -8x_7 &amp;= 1\\
-x_1  - 4x_2 + 2x_3 +4x_4 + 8x_5 - 31x_6 + 37x_7 &amp;= 4
\end{align*} </paragraphs>
              <newcol course="Math 1030" chapter="7" chapter_type="" section="2" subsection="" subsubsection="" environment="newcol" wbtag="newcol">
                <paragraphs course="Math 1030" chapter="7" chapter_type="" section="2" subsection="" subsubsection="" environment="newcol" wbtag="paragraphs"> This system has a $4\times 8$ augmented matrix
\[\left[\begin{array}[]{ccccccc|c}1&amp;4&amp;0&amp;-1&amp;0&amp;7&amp;-9&amp;3\\
2&amp;8&amp;-1&amp;3&amp;9&amp;-13&amp;7&amp;9\\
0&amp;0&amp;2&amp;-3&amp;-4&amp;12&amp;-8&amp;1\\
-1&amp;-4&amp;2&amp;4&amp;8&amp;-31&amp;37&amp;4\end{array}\right]\]
The matrix is row-equivalent to the following matrix reduced row-echelon form
(</paragraphs>
                <strong xmlns="http://www.w3.org/1999/xhtml" environment="newcol">
                  <paragraphs xmlns="http://www.math.cuhk.edu.hk/~pschan/cranach" course="Math 1030" chapter="7" chapter_type="" section="2" subsection="" subsubsection="" environment="newcol" wbtag="paragraphs">exercise</paragraphs>
                </strong>
                <paragraphs course="Math 1030" chapter="7" chapter_type="" section="2" subsection="" subsubsection="" environment="newcol" wbtag="paragraphs">: check this)</paragraphs>
                <newline course="Math 1030" chapter="7" chapter_type="" section="2" subsection="" subsubsection="" environment="newcol"/>
                <collapse course="Math 1030" chapter="7" chapter_type="" section="2" subsection="" subsubsection="" environment="newcol" wbtag="collapse">
                  <paragraphs course="Math 1030" chapter="7" chapter_type="" section="2" subsection="" subsubsection="" environment="newcol" wbtag="paragraphs"> \[\left[\begin{array}[]{ccccccc|c}\boxed{1}&amp;4&amp;0&amp;0&amp;2&amp;1&amp;-3&amp;4\\
0&amp;0&amp;\boxed{1}&amp;0&amp;1&amp;-3&amp;5&amp;2\\
0&amp;0&amp;0&amp;\boxed{1}&amp;2&amp;-6&amp;6&amp;1\\
0&amp;0&amp;0&amp;0&amp;0&amp;0&amp;0&amp;0\end{array}\right]\]
So we find that $r=3$ and
\[\displaystyle D=\{d_{1},\,d_{2},\,d_{3}\}=\{1,\,3,\,4\}\]
Let $i$ denote any one of the $r=3$ nonzero rows. Then the index $d_{i}$ is a pivot column. It will be easy in this case to use the equation represented by row $i$ to write an expression for the variable $x_{d_{i}}$. It will be a linear function of the variables $x_{f_{1}},\,x_{f_{2}},\,x_{f_{3}},\,x_{f_{4}}$</paragraphs>
                  <newline course="Math 1030" chapter="7" chapter_type="" section="2" subsection="" subsubsection="" environment="newcol"/>
                  <collapse course="Math 1030" chapter="7" chapter_type="" section="2" subsection="" subsubsection="" environment="newcol" wbtag="collapse">
                    <paragraphs course="Math 1030" chapter="7" chapter_type="" section="2" subsection="" subsubsection="" environment="newcol" wbtag="paragraphs"> \begin{align*}
(i=1)&amp; &amp; x_{d_1}&amp;=x_1=4-4x_2-2x_5-x_6+3x_7\\
(i=2)&amp; &amp; x_{d_2}&amp;=x_3=2-x_5+3x_6-5x_7\\
(i=3)&amp; &amp; x_{d_3}&amp;=x_4=1-2x_5+6x_6-6x_7
\end{align*} </paragraphs>
                    <collapse course="Math 1030" chapter="7" chapter_type="" section="2" subsection="" subsubsection="" environment="newcol" wbtag="collapse">
                      <paragraphs course="Math 1030" chapter="7" chapter_type="" section="2" subsection="" subsubsection="" environment="newcol" wbtag="paragraphs"> Each element of the set $F=\{f_{1},\,f_{2},\,f_{3},\,f_{4},\,f_{5}\}=\{2,\,5,\,6,\,7,\,8\}$ is the index of a variable, except for $f_{5}=8$. We refer to $x_{f_{1}}=x_{2}$, $x_{f_{2}}=x_{5}$, $x_{f_{3}}=x_{6}$ and $x_{f_{4}}=x_{7}$ as </paragraphs>
                      <inline_keyword course="Math 1030" chapter="7" chapter_type="" section="2" subsection="" subsubsection="" environment="newcol">free</inline_keyword>
                      <paragraphs course="Math 1030" chapter="7" chapter_type="" section="2" subsection="" subsubsection="" environment="newcol" wbtag="paragraphs"> (or </paragraphs>
                      <inline_keyword course="Math 1030" chapter="7" chapter_type="" section="2" subsection="" subsubsection="" environment="newcol">independent</inline_keyword>
                      <paragraphs course="Math 1030" chapter="7" chapter_type="" section="2" subsection="" subsubsection="" environment="newcol" wbtag="paragraphs">) variables since they are allowed to assume any possible combination of values that we can imagine and we can continue on to build a solution to the system by solving individual equations for the values of the other (</paragraphs>
                      <inline_keyword course="Math 1030" chapter="7" chapter_type="" section="2" subsection="" subsubsection="" environment="newcol">dependent</inline_keyword>
                      <paragraphs course="Math 1030" chapter="7" chapter_type="" section="2" subsection="" subsubsection="" environment="newcol" wbtag="paragraphs">) variables.</paragraphs>
                      <newline course="Math 1030" chapter="7" chapter_type="" section="2" subsection="" subsubsection="" environment="newcol"/>
                      <collapse course="Math 1030" chapter="7" chapter_type="" section="2" subsection="" subsubsection="" environment="newcol" wbtag="collapse">
                        <paragraphs course="Math 1030" chapter="7" chapter_type="" section="2" subsection="" subsubsection="" environment="newcol" wbtag="paragraphs"> Each element of the set $D=\{d_{1},\,d_{2},\,d_{3}\}=\{1,\,3,\,4\}$ is the index of a variable. We refer to the variables $x_{d_{1}}=x_{1}$, $x_{d_{2}}=x_{3}$ and $x_{d_{3}}=x_{4}$ as </paragraphs>
                        <inline_keyword course="Math 1030" chapter="7" chapter_type="" section="2" subsection="" subsubsection="" environment="newcol">dependent</inline_keyword>
                        <paragraphs course="Math 1030" chapter="7" chapter_type="" section="2" subsection="" subsubsection="" environment="newcol" wbtag="paragraphs"> variables since they depend on the independent variables. More precisely, for each possible choice of values for the independent variables we get exactly one set of values for the dependent variables that combine to form a solution of the system.</paragraphs>
                        <newline course="Math 1030" chapter="7" chapter_type="" section="2" subsection="" subsubsection="" environment="newcol"/>
                        <collapse course="Math 1030" chapter="7" chapter_type="" section="2" subsection="" subsubsection="" environment="newcol" wbtag="collapse">
                          <paragraphs course="Math 1030" chapter="7" chapter_type="" section="2" subsection="" subsubsection="" environment="newcol" wbtag="paragraphs"> To express the solutions as a set, we write
\begin{equation}\left\{\left.\begin{bmatrix}
4-4x_{2}-2x_{5}-x_{6}+3x_{7}\\
x_{2}\\
2-x_{5}+3x_{6}-5x_{7}\\
1-2x_{5}+6x_{6}-6x_{7}\\
x_{5}\\
x_{6}\\
x_{7}\end{bmatrix}\,\right|\,x_{2},\,x_{5},\,x_{6},\,x_{7}\in \mathbb{R}\right\}
\end{equation}
or equivalently:
\[
\left\{\left.
\colvector{4\\0\\2\\1\\0\\0\\0}
+
x_2\colvector{-4\\1\\0\\0\\0\\0\\0}
+
x_5\colvector{-2\\ 0\\ -1\\ -2\\ 1\\ 0\\ 0}
+
x_6\colvector{-1\\ 0\\ 3\\ 6\\ 0\\ 1\\ 0}
+
x_7\colvector{3\\ 0\\ -5\\ -6\\ 0\\ 0\\ 1}
\,\right|\,
x_2, x_5, x_6, x_7 \in \mathbb{R}
\right\}
\] </paragraphs>
                          <collapse course="Math 1030" chapter="7" chapter_type="" section="2" subsection="" subsubsection="" environment="newcol" wbtag="collapse">
                            <paragraphs course="Math 1030" chapter="7" chapter_type="" section="2" subsection="" subsubsection="" environment="newcol" wbtag="paragraphs"> The condition that $x_{2},\,x_{5},\,x_{6},\,x_{7}$ are real numbers is how we specify that the variables $x_{2},\,x_{5},\,x_{6},\,x_{7}$ are </paragraphs>
                            <strong xmlns="http://www.w3.org/1999/xhtml" environment="newcol">
                              <paragraphs xmlns="http://www.math.cuhk.edu.hk/~pschan/cranach" course="Math 1030" chapter="7" chapter_type="" section="2" subsection="" subsubsection="" environment="newcol" wbtag="paragraphs">free</paragraphs>
                            </strong>
                            <paragraphs course="Math 1030" chapter="7" chapter_type="" section="2" subsection="" subsubsection="" environment="newcol" wbtag="paragraphs"> to assume any possible values.</paragraphs>
                            <newline course="Math 1030" chapter="7" chapter_type="" section="2" subsection="" subsubsection="" environment="newcol"/>
                            <collapse course="Math 1030" chapter="7" chapter_type="" section="2" subsection="" subsubsection="" environment="newcol" wbtag="collapse">
                              <paragraphs course="Math 1030" chapter="7" chapter_type="" section="2" subsection="" subsubsection="" environment="newcol" wbtag="paragraphs"> This systematic approach to solving a system of equations will allow us to create a precise description of the solution set for any consistent system once we have found the reduced row-echelon form of the augmented matrix. It will work just as well when the set of free variables is empty and we get just a single solution. </paragraphs>
                            </collapse>
                          </collapse>
                        </collapse>
                      </collapse>
                    </collapse>
                  </collapse>
                </collapse>
              </newcol>
            </statement>
          </slide>
          <slide environment="" chapter_type="Chapter" wbtag="slide" canon_num="7" id="s7" slide="7" course="Math 1030" chapter="7" section="2" subsection="" subsubsection="" chapter_title="Types of Solution Sets" section_title="Consistent Systems">
            <keywords slide="7" environ="slide" chapter="7" course="Math 1030">
              <keyword chapter="7" slide="7">dependent variable</keyword>
              <keyword chapter="7" slide="7">independent variable</keyword>
              <keyword chapter="7" slide="7">free variable</keyword>
              <keyword chapter="7" slide="7">Free and dependent variables</keyword>
              <keyword chapter="7" slide="7">Independent and Dependent Variables</keyword>
            </keywords>
            <hc_keyword course="Math 1030" chapter="7" chapter_type="" section="2" subsection="" subsubsection="" environment="" wbtag="hc_keyword" class="hidden">dependent variable</hc_keyword>
            <hc_keyword course="Math 1030" chapter="7" chapter_type="" section="2" subsection="" subsubsection="" environment="" wbtag="hc_keyword" class="hidden">independent variable</hc_keyword>
            <hc_keyword course="Math 1030" chapter="7" chapter_type="" section="2" subsection="" subsubsection="" environment="" wbtag="hc_keyword" class="hidden">free variable</hc_keyword>
            <statement environment="statement" chapter_type="Chapter" type="Definition" wbtag="defn" num="4" title="Independent and Dependent Variables" md5="785bd51879922b3e82997b7d0e254719" course="Math 1030" chapter="7" slide="7" item="7.4">
              <title environment="title" chapter_type="Chapter" wbtag="statement" scope="" course="Math 1030" chapter="7" section="2" subsection="" subsubsection="" serial="" slide="7">Independent and Dependent Variables</title>
              <label wbtag="label" name="IDV" type="Definition"/>
              <paragraphs course="Math 1030" chapter="7" chapter_type="" section="2" subsection="" subsubsection="" environment="statement" wbtag="paragraphs"> Suppose $A$ is the augmented matrix of a consistent system of linear equations and $B$ is a row-equivalent matrix in reduced row-echelon form.
Suppose $j$ is the index of a pivot column of $B$. Then the variable $x_{j}$ is </paragraphs>
              <strong xmlns="http://www.w3.org/1999/xhtml" environment="statement">
                <paragraphs xmlns="http://www.math.cuhk.edu.hk/~pschan/cranach" course="Math 1030" chapter="7" chapter_type="" section="2" subsection="" subsubsection="" environment="statement" wbtag="paragraphs">dependent</paragraphs>
              </strong>
              <paragraphs course="Math 1030" chapter="7" chapter_type="" section="2" subsection="" subsubsection="" environment="statement" wbtag="paragraphs">.
A variable that is not dependent is called </paragraphs>
              <strong xmlns="http://www.w3.org/1999/xhtml" environment="statement">
                <paragraphs xmlns="http://www.math.cuhk.edu.hk/~pschan/cranach" course="Math 1030" chapter="7" chapter_type="" section="2" subsection="" subsubsection="" environment="statement" wbtag="paragraphs">independent</paragraphs>
              </strong>
              <paragraphs course="Math 1030" chapter="7" chapter_type="" section="2" subsection="" subsubsection="" environment="statement" wbtag="paragraphs"> or </paragraphs>
              <strong xmlns="http://www.w3.org/1999/xhtml" environment="statement">
                <paragraphs xmlns="http://www.math.cuhk.edu.hk/~pschan/cranach" course="Math 1030" chapter="7" chapter_type="" section="2" subsection="" subsubsection="" environment="statement" wbtag="paragraphs">free</paragraphs>
              </strong>
              <paragraphs course="Math 1030" chapter="7" chapter_type="" section="2" subsection="" subsubsection="" environment="statement" wbtag="paragraphs">. </paragraphs>
            </statement>
            <hc_keyword course="Math 1030" chapter="7" chapter_type="" section="2" subsection="" subsubsection="" environment="" wbtag="hc_keyword" class="hidden">Free and dependent variables</hc_keyword>
            <statement environment="statement" chapter_type="Chapter" type="Example" wbtag="eg" num="5" md5="33db8c3ae0574e92845c99171b17587a" course="Math 1030" chapter="7" slide="7" item="7.5">
              <label wbtag="label" name="FDV" type="Example"/>
              <newline course="Math 1030" chapter="7" chapter_type="" section="2" subsection="" subsubsection="" environment="statement"/>
              <newcol course="Math 1030" chapter="7" chapter_type="" section="2" subsection="" subsubsection="" environment="newcol" wbtag="newcol">
                <paragraphs course="Math 1030" chapter="7" chapter_type="" section="2" subsection="" subsubsection="" environment="newcol" wbtag="paragraphs"> Consider the system of five equations in five variables,
\begin{align*}
x_1  - x_2  -2 x_3 +  x_4 + 11 x_5 &amp;= 13 \\
x_1 - x_2 +  x_3+  x_4 + 5 x_5 &amp;= 16 \\
2 x_1  -2 x_2       +  x_4 + 10 x_5 &amp;= 21 \\
2 x_1  -2 x_2  - x_3 + 3 x_4 + 20 x_5 &amp;= 38 \\
2 x_1  -2 x_ 2 +  x_3 +  x_4 + 8 x_ 5&amp;= 22
\end{align*}
whose augmented matrix row-reduces to:</paragraphs>
                <newline course="Math 1030" chapter="7" chapter_type="" section="2" subsection="" subsubsection="" environment="newcol"/>
                <collapse course="Math 1030" chapter="7" chapter_type="" section="2" subsection="" subsubsection="" environment="newcol" wbtag="collapse">
                  <paragraphs course="Math 1030" chapter="7" chapter_type="" section="2" subsection="" subsubsection="" environment="newcol" wbtag="paragraphs"> \begin{equation}
\left[\begin{array}[]{ccccc|c}\boxed{1}&amp;-1&amp;0&amp;0&amp;3&amp;6\\
0&amp;0&amp;\boxed{1}&amp;0&amp;-2&amp;1\\
0&amp;0&amp;0&amp;\boxed{1}&amp;4&amp;9\\
0&amp;0&amp;0&amp;0&amp;0&amp;0\\
0&amp;0&amp;0&amp;0&amp;0&amp;0\end{array}\right]
\end{equation} </paragraphs>
                  <collapse course="Math 1030" chapter="7" chapter_type="" section="2" subsection="" subsubsection="" environment="newcol" wbtag="collapse">
                    <paragraphs course="Math 1030" chapter="7" chapter_type="" section="2" subsection="" subsubsection="" environment="newcol" wbtag="paragraphs"> Columns 1, 3 and 4 are pivot columns, so $D=\{1,\,3,\,4\}$. From this we know that the variables $x_{1}$, $x_{3}$ and $x_{4}$ will be dependent variables, and each of the $r=3$ nonzero rows of the row-reduced matrix will yield an expression for one of these three variables. The set $F$ is all the remaining column indices, $F=\{2,\,5,\,6\}$. The column index $6$ in $F$ means that the final column is not a pivot column, and thus the system is consistent (see the next theorem). The remaining indices in $F$ indicate free variables, so $x_{2}$ and $x_{5}$ (the remaining variables) are our free variables. The resulting three equations that describe our solution set are then,</paragraphs>
                    <newline course="Math 1030" chapter="7" chapter_type="" section="2" subsection="" subsubsection="" environment="newcol"/>
                    <collapse course="Math 1030" chapter="7" chapter_type="" section="2" subsection="" subsubsection="" environment="newcol" wbtag="collapse">
                      <paragraphs course="Math 1030" chapter="7" chapter_type="" section="2" subsection="" subsubsection="" environment="newcol" wbtag="paragraphs"> \begin{align*}
(x_{d_1}=x_1)&amp; &amp; x_1&amp;=6+x_2-3x_5\\
(x_{d_2}=x_3)&amp; &amp; x_3&amp;=1+2x_5\\
(x_{d_3}=x_4)&amp; &amp; x_4&amp;=9-4x_5
\end{align*} </paragraphs>
                      <collapse course="Math 1030" chapter="7" chapter_type="" section="2" subsection="" subsubsection="" environment="newcol" wbtag="collapse">
                        <paragraphs course="Math 1030" chapter="7" chapter_type="" section="2" subsection="" subsubsection="" environment="newcol" wbtag="paragraphs"> Make sure you understand where these three equations came from, and notice how the location of the pivot columns determined the variables on the left-hand side of each equation. We can compactly describe the solution set as,
\begin{equation}
S=\left\{\left.\begin{bmatrix}6+x_{2}-3x_{5}\\
x_{2}\\
1+2x_{5}\\
9-4x_{5}\\
x_{5}\end{bmatrix}\,\right|\,x_{2},\,x_{5}\text{ real numbers}\right\}
\end{equation} </paragraphs>
                        <collapse course="Math 1030" chapter="7" chapter_type="" section="2" subsection="" subsubsection="" environment="newcol" wbtag="collapse">
                          <paragraphs course="Math 1030" chapter="7" chapter_type="" section="2" subsection="" subsubsection="" environment="newcol" wbtag="paragraphs"> Notice how we express the freedom for $x_{2}$ and $x_{5}$: $x_{2},\,x_{5}\text{ real numbers}$. </paragraphs>
                        </collapse>
                      </collapse>
                    </collapse>
                  </collapse>
                </collapse>
              </newcol>
            </statement>
          </slide>
          <slide environment="" chapter_type="Chapter" wbtag="slide" canon_num="8" id="s8" slide="8" course="Math 1030" chapter="7" section="2" subsection="" subsubsection="" chapter_title="Types of Solution Sets" section_title="Consistent Systems">
            <keywords slide="8" environ="slide" chapter="7" course="Math 1030">
              <keyword chapter="7" slide="8">inconsistent</keyword>
              <keyword chapter="7" slide="8">consistent</keyword>
              <keyword chapter="7" slide="8">consistent</keyword>
              <keyword chapter="7" slide="8">non-zero row</keyword>
              <keyword chapter="7" slide="8">Recognizing Consistency of a Linear System</keyword>
            </keywords>
            <statement environment="statement" chapter_type="Chapter" type="Theorem" wbtag="thm" num="6" title="Recognizing Consistency of a Linear System" md5="f3386ff26bec659ea2917f653af3eb7e" course="Math 1030" chapter="7" slide="8" item="7.6">
              <title environment="title" chapter_type="Chapter" wbtag="statement" scope="" course="Math 1030" chapter="7" section="2" subsection="" subsubsection="" serial="" slide="8">Recognizing Consistency of a Linear System</title>
              <label wbtag="label" name="RCLS" type="Theorem"/>
              <paragraphs course="Math 1030" chapter="7" chapter_type="" section="2" subsection="" subsubsection="" environment="statement" wbtag="paragraphs"> Suppose $A$ is the augmented matrix of a system of linear equations with $n$ variables. Suppose also that $B$ is a row-equivalent matrix in reduced row-echelon form with $r$ nonzero rows. </paragraphs>
              <col_ul course="Math 1030" chapter="7" chapter_type="" section="2" subsection="" subsubsection="" environment="col_ul" wbtag="col_ul">
                <col_li course="Math 1030" chapter="7" chapter_type="" section="2" subsection="" subsubsection="" environment="col_ul" wbtag="col_li">
                  <paragraphs course="Math 1030" chapter="7" chapter_type="" section="2" subsection="" subsubsection="" environment="col_ul" wbtag="paragraphs"> Then the system of equations is </paragraphs>
                  <inline_keyword course="Math 1030" chapter="7" chapter_type="" section="2" subsection="" subsubsection="" environment="col_ul">inconsistent</inline_keyword>
                  <paragraphs course="Math 1030" chapter="7" chapter_type="" section="2" subsection="" subsubsection="" environment="col_ul" wbtag="paragraphs"> if and only if column $n+1$ (i.e., the last column) of $B$ is a pivot column. </paragraphs>
                </col_li>
                <col_li course="Math 1030" chapter="7" chapter_type="" section="2" subsection="" subsubsection="" environment="col_ul" wbtag="col_li">
                  <paragraphs course="Math 1030" chapter="7" chapter_type="" section="2" subsection="" subsubsection="" environment="col_ul" wbtag="paragraphs"> Equivalently a system is </paragraphs>
                  <inline_keyword course="Math 1030" chapter="7" chapter_type="" section="2" subsection="" subsubsection="" environment="col_ul">consistent</inline_keyword>
                  <paragraphs course="Math 1030" chapter="7" chapter_type="" section="2" subsection="" subsubsection="" environment="col_ul" wbtag="paragraphs"> if and only if column $n+1$ is not a pivot column of $B$. </paragraphs>
                </col_li>
                <col_li course="Math 1030" chapter="7" chapter_type="" section="2" subsection="" subsubsection="" environment="col_ul" wbtag="col_li">
                  <paragraphs course="Math 1030" chapter="7" chapter_type="" section="2" subsection="" subsubsection="" environment="col_ul" wbtag="paragraphs"> Another way of expressing the theorem is to say that
a system of linear equations is </paragraphs>
                  <inline_keyword course="Math 1030" chapter="7" chapter_type="" section="2" subsection="" subsubsection="" environment="col_ul">consistent</inline_keyword>
                  <paragraphs course="Math 1030" chapter="7" chapter_type="" section="2" subsection="" subsubsection="" environment="col_ul" wbtag="paragraphs"> if and only if the last </paragraphs>
                  <inline_keyword course="Math 1030" chapter="7" chapter_type="" section="2" subsection="" subsubsection="" environment="col_ul">non-zero row</inline_keyword>
                  <paragraphs course="Math 1030" chapter="7" chapter_type="" section="2" subsection="" subsubsection="" environment="col_ul" wbtag="paragraphs"> is not $(0,0,\ldots,0,1)$. </paragraphs>
                </col_li>
              </col_ul>
            </statement>
            <substatement environment="substatement" chapter_type="Chapter" type="Proof" wbtag="proof" md5="6cb58ca4b733d44b67d3b7b6c6831435" course="Math 1030" chapter="7" slide="8" of="f3386ff26bec659ea2917f653af3eb7e" of-src-course="Math 1030" of-src-chapter="7" of-src-slide="8" of-type="Theorem" of-item="7.6" of-src-filename="lec7.xml" ofmd5="f3386ff26bec659ea2917f653af3eb7e" of-serial="">
              <of-title>Recognizing Consistency of a Linear System</of-title>
              <newcol course="Math 1030" chapter="7" chapter_type="" section="2" subsection="" subsubsection="" environment="newcol" wbtag="newcol">
                <paragraphs course="Math 1030" chapter="7" chapter_type="" section="2" subsection="" subsubsection="" environment="newcol" wbtag="paragraphs"> (sketch, for details, see Beezer, Ver 3.5 print version p.38, proof of theorem RCLS, you can skip the proof in the textbook)
If the last column vector of $B$ is a pivot column, then $B$ is in the form of:</paragraphs>
                <newline course="Math 1030" chapter="7" chapter_type="" section="2" subsection="" subsubsection="" environment="newcol"/>
                <collapse course="Math 1030" chapter="7" chapter_type="" section="2" subsection="" subsubsection="" environment="newcol" wbtag="collapse">
                  <paragraphs course="Math 1030" chapter="7" chapter_type="" section="2" subsection="" subsubsection="" environment="newcol" wbtag="paragraphs"> \[\begin{bmatrix}
1 &amp; \cdots &amp; 0 &amp; \cdots &amp; 0 &amp; \cdots &amp; * &amp; 0\\
&amp;        &amp; 1 &amp; \cdots &amp; 0 &amp; \cdots &amp; * &amp; 0\\
&amp;        &amp;   &amp;        &amp; 1 &amp; \cdots &amp; * &amp; 0\\
\vdots&amp;\vdots&amp;\vdots&amp;\vdots&amp;\vdots&amp;\vdots&amp;\vdots&amp;\vdots\\
0 &amp; \cdots &amp; 0 &amp; \cdots &amp; 0 &amp; \cdots &amp; 0 &amp;1\\
0 &amp; \cdots &amp; 0 &amp; \cdots &amp; 0 &amp; \cdots &amp; 0 &amp;0\\
&amp;&amp;&amp;&amp;&amp;&amp;&amp;
\end{bmatrix}\]
For the system of linear equations with the above augmented matrix, the $r+1$-st equation (i.e. the last non-zero equation) is
\[0=1.\]
So the system of linear equations has no solution.
Conversely, if the last column vector is not a pivot column vector, then $B$ is in the form of:</paragraphs>
                  <newline course="Math 1030" chapter="7" chapter_type="" section="2" subsection="" subsubsection="" environment="newcol"/>
                  <collapse course="Math 1030" chapter="7" chapter_type="" section="2" subsection="" subsubsection="" environment="newcol" wbtag="collapse">
                    <paragraphs course="Math 1030" chapter="7" chapter_type="" section="2" subsection="" subsubsection="" environment="newcol" wbtag="paragraphs"> \[\begin{bmatrix}
1 &amp; \cdots &amp; 0 &amp; \cdots &amp; 0 &amp; \cdots &amp; 0 &amp; \cdots\\
&amp;        &amp; 1 &amp; \cdots &amp; 0 &amp; \cdots &amp; 0 &amp; \cdots\\
&amp;        &amp;   &amp;        &amp; 1 &amp; \cdots &amp; 0 &amp; \cdots\\
\vdots&amp;\vdots&amp;\vdots&amp;\vdots&amp;\vdots&amp;\vdots&amp;\vdots&amp;\vdots\\
0 &amp; \cdots &amp; 0 &amp; \cdots &amp; 0 &amp; \cdots &amp; 1 &amp; \cdots\\
0 &amp; \cdots &amp; 0 &amp; \cdots &amp; 0 &amp; \cdots &amp; 0 &amp;0\\
&amp;&amp;&amp;&amp;&amp;&amp;&amp;
\end{bmatrix}\]
For the system of equations with the above augmented matrix,
we can move the variables corresponding to the non-pivot columns (i.e., $x_{f_{1}},x_{f_{2}},\ldots$) to the right hand side of the equations and therefore solve the equations.
Hence it is consistent.
Note that $x_{f_{1}},x_{f_{2}},\ldots$ are free variables. </paragraphs>
                    <qed course="Math 1030" chapter="7" chapter_type="" section="2" subsection="" subsubsection="" environment="newcol"/>
                  </collapse>
                </collapse>
              </newcol>
            </substatement>
          </slide>
          <slide environment="" chapter_type="Chapter" wbtag="slide" canon_num="9" id="s9" slide="9" course="Math 1030" chapter="7" section="2" subsection="" subsubsection="" chapter_title="Types of Solution Sets" section_title="Consistent Systems">
            <keywords slide="9" environ="slide" chapter="7" course="Math 1030"/>
            <statement environment="statement" chapter_type="Chapter" type="Example" wbtag="eg" num="7" md5="a39a40164cc1fecb1ab3c271739df049" course="Math 1030" chapter="7" slide="9" item="7.7">
              <paragraphs course="Math 1030" chapter="7" chapter_type="" section="2" subsection="" subsubsection="" environment="statement" wbtag="paragraphs"> Determine if the following system of linear equation is consistent.
\begin{align*}
x_1+x_2+2 x_3+3 x_4+2 x_5+5 x_6 &amp;=1 \\
2 x_1+2 x_2+3 x_3-x_4 &amp;=1 \\
3 x_1+3 x_2+5 x_3+x_4+x_5-2 x_6 &amp;=3 \\
x_4+x_5+7 x_6 &amp;=0
\end{align*} </paragraphs>
              <newcol course="Math 1030" chapter="7" chapter_type="" section="2" subsection="" subsubsection="" environment="newcol" wbtag="newcol">
                <paragraphs course="Math 1030" chapter="7" chapter_type="" section="2" subsection="" subsubsection="" environment="newcol" wbtag="paragraphs"> The augmented matrix is
\[\left[\begin{array}[]{cccccc|c}1&amp;1&amp;2&amp;3&amp;2&amp;5&amp;1\\
2&amp;2&amp;3&amp;-1&amp;0&amp;0&amp;1\\
3&amp;3&amp;5&amp;1&amp;1&amp;-2&amp;3\\
0&amp;0&amp;0&amp;1&amp;1&amp;7&amp;-1\\
\end{array}\right]\] </paragraphs>
                <collapse course="Math 1030" chapter="7" chapter_type="" section="2" subsection="" subsubsection="" environment="newcol" wbtag="collapse">
                  <paragraphs course="Math 1030" chapter="7" chapter_type="" section="2" subsection="" subsubsection="" environment="newcol" wbtag="paragraphs"> The reduced row echelon form is
\[\left[\begin{array}[]{cccccc|c}1&amp;1&amp;0&amp;0&amp;5&amp;62&amp;0\\
0&amp;0&amp;1&amp;0&amp;-3&amp;-39&amp;0\\
0&amp;0&amp;0&amp;1&amp;1&amp;7&amp;0\\
0&amp;0&amp;0&amp;0&amp;0&amp;0&amp;1\\
\end{array}\right]\] </paragraphs>
                  <collapse course="Math 1030" chapter="7" chapter_type="" section="2" subsection="" subsubsection="" environment="newcol" wbtag="collapse">
                    <paragraphs course="Math 1030" chapter="7" chapter_type="" section="2" subsection="" subsubsection="" environment="newcol" wbtag="paragraphs"> The last column is a pivot column. So the system is inconsistent. </paragraphs>
                  </collapse>
                </collapse>
              </newcol>
            </statement>
            <statement environment="statement" chapter_type="Chapter" type="Example" wbtag="eg" num="8" md5="7e4b9c8dba355727a6e2afed99ab1bc5" course="Math 1030" chapter="7" slide="9" item="7.8">
              <newcol course="Math 1030" chapter="7" chapter_type="" section="2" subsection="" subsubsection="" environment="newcol" wbtag="newcol">
                <paragraphs course="Math 1030" chapter="7" chapter_type="" section="2" subsection="" subsubsection="" environment="newcol" wbtag="paragraphs"> Determine if the following system of linear equation is consistent.
\begin{align*}
x_1+x_2+2 x_3+3 x_4+2 x_5+5 x_6 &amp;=1 \\
2 x_1+2 x_2+3 x_3-x_4 &amp;=1 \\
3 x_1+3 x_2+5 x_3+x_4+x_5-2 x_6 &amp;=3 \\
x_4+x_5+7 x_6 &amp;=-1
\end{align*} </paragraphs>
                <collapse course="Math 1030" chapter="7" chapter_type="" section="2" subsection="" subsubsection="" environment="newcol" wbtag="collapse">
                  <paragraphs course="Math 1030" chapter="7" chapter_type="" section="2" subsection="" subsubsection="" environment="newcol" wbtag="paragraphs"> The augmented matrix is
\[\left[\begin{array}[]{cccccc|c}1&amp;1&amp;2&amp;3&amp;2&amp;5&amp;1\\
2&amp;2&amp;3&amp;-1&amp;0&amp;0&amp;1\\
3&amp;3&amp;5&amp;1&amp;1&amp;-2&amp;3\\
0&amp;0&amp;0&amp;1&amp;1&amp;7&amp;-1\\
\end{array}\right]\] </paragraphs>
                  <collapse course="Math 1030" chapter="7" chapter_type="" section="2" subsection="" subsubsection="" environment="newcol" wbtag="collapse">
                    <paragraphs course="Math 1030" chapter="7" chapter_type="" section="2" subsection="" subsubsection="" environment="newcol" wbtag="paragraphs"> The reduced row echelon form is
\[\left[\begin{array}[]{cccccc|c}1&amp;1&amp;0&amp;0&amp;5&amp;62&amp;-12\\
0&amp;0&amp;1&amp;0&amp;-3&amp;-39&amp;8\\
0&amp;0&amp;0&amp;1&amp;1&amp;7&amp;-1\\
0&amp;0&amp;0&amp;0&amp;0&amp;0&amp;0\\
\end{array}\right]\] </paragraphs>
                    <collapse course="Math 1030" chapter="7" chapter_type="" section="2" subsection="" subsubsection="" environment="newcol" wbtag="collapse">
                      <paragraphs course="Math 1030" chapter="7" chapter_type="" section="2" subsection="" subsubsection="" environment="newcol" wbtag="paragraphs"> The last column is not a pivot column. So the system is consistent. </paragraphs>
                    </collapse>
                  </collapse>
                </collapse>
              </newcol>
            </statement>
          </slide>
          <slide environment="" chapter_type="Chapter" wbtag="slide" canon_num="10" id="s10" slide="10" course="Math 1030" chapter="7" section="2" subsection="" subsubsection="" chapter_title="Types of Solution Sets" section_title="Consistent Systems">
            <keywords slide="10" environ="slide" chapter="7" course="Math 1030">
              <keyword chapter="7" slide="10">Consistent Systems r and n</keyword>
            </keywords>
            <statement environment="statement" chapter_type="Chapter" type="Theorem" wbtag="thm" num="9" title="Consistent Systems r and n" md5="d2c8db147df80ef12421ed89e4fb12e5" course="Math 1030" chapter="7" slide="10" item="7.9">
              <title environment="title" chapter_type="Chapter" wbtag="statement" scope="" course="Math 1030" chapter="7" section="2" subsection="" subsubsection="" serial="" slide="10">Consistent Systems, $r$ and $n$</title>
              <label wbtag="label" name="CSRN" type="Theorem"/>
              <paragraphs course="Math 1030" chapter="7" chapter_type="" section="2" subsection="" subsubsection="" environment="statement" wbtag="paragraphs"> Suppose $A$ is the augmented matrix of a consistent system of linear equations with $n$ variables. Suppose also that $B$ is a row-equivalent matrix in reduced row-echelon form with $r$ pivot columns. Then $r\leq n$. If $r=n$, then the system has a unique solution, and if $r &lt; n$, then the system has infinitely many solutions. </paragraphs>
            </statement>
            <substatement environment="substatement" chapter_type="Chapter" type="Proof" wbtag="proof" md5="f4281a12d684955d732eb84fd3321c21" course="Math 1030" chapter="7" slide="10" of="d2c8db147df80ef12421ed89e4fb12e5" of-src-course="Math 1030" of-src-chapter="7" of-src-slide="10" of-type="Theorem" of-item="7.9" of-src-filename="lec7.xml" ofmd5="d2c8db147df80ef12421ed89e4fb12e5" of-serial="">
              <of-title>Consistent Systems, $r$ and $n$</of-title>
              <newcol course="Math 1030" chapter="7" chapter_type="" section="2" subsection="" subsubsection="" environment="newcol" wbtag="newcol">
                <paragraphs course="Math 1030" chapter="7" chapter_type="" section="2" subsection="" subsubsection="" environment="newcol" wbtag="paragraphs"> This theorem contains three implications that we must establish.
Notice first that $B$ has $n+1$ columns, so there can be at most $n+1$ pivot columns, i.e., $r\leq n+1$.
If $r=n+1$, then every column of $B$ is a pivot column, and in particular, the last column is a pivot column.
So the previous theorem tells us that the system is inconsistent, contrary to our hypothesis. We are left with $r\leq n$.</paragraphs>
                <newline course="Math 1030" chapter="7" chapter_type="" section="2" subsection="" subsubsection="" environment="newcol"/>
                <paragraphs course="Math 1030" chapter="7" chapter_type="" section="2" subsection="" subsubsection="" environment="newcol" wbtag="paragraphs">When $r=n$, we find $n-r=0$ free variables (i.e., $F=\{n+1\}$) and the only solution is given by setting the $n$ variables to the the first $n$ entries of column $n+1$ of $B$.
When $r &lt; n$, we have $n-r &gt; 0$ free variables. Choose one free variable and set all the other free variables to zero. Now, set the chosen free variable to any fixed value. It is possible to then determine the values of the dependent variables to create a solution to the system. By setting the chosen free variable to different values, in this manner we can create infinitely many solutions. </paragraphs>
                <qed course="Math 1030" chapter="7" chapter_type="" section="2" subsection="" subsubsection="" environment="newcol"/>
              </newcol>
            </substatement>
          </slide>
        </slides>
      </section>
      <section environment="" chapter_type="" type="Section" wbtag="section" title="Free variables" course="Math 1030" chapter="7" num="3" serial="7.3">
        <title environment="title" chapter_type="Chapter" wbtag="title" scope="section" course="Math 1030" chapter="7" section="3" subsection="" subsubsection="" serial="7.3" slide="">
          <paragraphs course="Math 1030" chapter="7" chapter_type="" section="3" subsection="" subsubsection="" environment="title" wbtag="paragraphs">Free variables</paragraphs>
        </title>
        <label wbtag="label" name="FV" type="Section"/>
        <slides environment="" chapter_type="">
          <slide environment="" chapter_type="Chapter" canon_num="11" scope="section" id="s11" slide="11" course="Math 1030" chapter="7" section="3" subsection="" subsubsection="" chapter_title="Types of Solution Sets" section_title="Free variables">
            <keywords slide="11" environ="slide" chapter="7" course="Math 1030">
              <keyword chapter="7" slide="11">Free Variables for Consistent Systems</keyword>
            </keywords>
            <title environment="title" chapter_type="Chapter" wbtag="title" scope="section" course="Math 1030" chapter="7" section="3" subsection="" subsubsection="" serial="" slide="11">
              <paragraphs course="Math 1030" chapter="7" chapter_type="" section="3" subsection="" subsubsection="" environment="title" wbtag="paragraphs">Free variables</paragraphs>
            </title>
            <paragraphs course="Math 1030" chapter="7" chapter_type="" section="3" subsection="" subsubsection="" environment="" wbtag="paragraphs"> The next theorem simply states a conclusion from the final paragraph of the previous proof, allowing us to state explicitly the number of free variables for a consistent system. </paragraphs>
            <statement environment="statement" chapter_type="Chapter" type="Theorem" wbtag="thm" num="10" title="Free Variables for Consistent Systems" md5="01735b5fcc1b220cc76b4c6ee324a616" course="Math 1030" chapter="7" slide="11" item="7.10">
              <title environment="title" chapter_type="Chapter" wbtag="statement" scope="" course="Math 1030" chapter="7" section="3" subsection="" subsubsection="" serial="" slide="11">Free Variables for Consistent Systems</title>
              <label wbtag="label" name="FVCS" type="Theorem"/>
              <paragraphs course="Math 1030" chapter="7" chapter_type="" section="3" subsection="" subsubsection="" environment="statement" wbtag="paragraphs"> Suppose $A$ is the augmented matrix of a consistent system of linear equations with $n$ variables. Suppose also that $B$ is a row-equivalent matrix in reduced row-echelon form with $r$ rows that are not completely zeros. Then the solution set can be described with $n-r$ free variables. </paragraphs>
            </statement>
          </slide>
          <slide environment="" chapter_type="Chapter" wbtag="slide" canon_num="12" id="s12" slide="12" course="Math 1030" chapter="7" section="3" subsection="" subsubsection="" chapter_title="Types of Solution Sets" section_title="Free variables">
            <keywords slide="12" environ="slide" chapter="7" course="Math 1030"/>
            <statement environment="statement" chapter_type="Chapter" type="Example" wbtag="eg" num="11" md5="f27df61a83d69577b0eb2eaad283966b" course="Math 1030" chapter="7" slide="12" item="7.11">
              <enumerate course="Math 1030" chapter="7" chapter_type="" section="3" subsection="" subsubsection="" environment="enumerate" wbtag="enumerate">
                <item course="Math 1030" chapter="7" chapter_type="" section="3" subsection="" subsubsection="" environment="enumerate" wbtag="item">
                  <paragraphs course="Math 1030" chapter="7" chapter_type="" section="3" subsection="" subsubsection="" environment="enumerate" wbtag="paragraphs"> System of linear equations with $n=3$, $m=3$.</paragraphs>
                  <newline course="Math 1030" chapter="7" chapter_type="" section="3" subsection="" subsubsection="" environment="enumerate"/>
                  <newcol course="Math 1030" chapter="7" chapter_type="" section="3" subsection="" subsubsection="" environment="newcol" wbtag="newcol">
                    <paragraphs course="Math 1030" chapter="7" chapter_type="" section="3" subsection="" subsubsection="" environment="newcol" wbtag="paragraphs"> \begin{align*}
x_1 -x_2 +2x_3 &amp; =1\\
2x_1+ x_2 + x_3 &amp; =8\\
x_1 + x_2 &amp; =5
\end{align*}
Augmented matrix
\[\left[\begin{array}[]{ccc|c}1&amp;-1&amp;2&amp;1\\
2&amp;1&amp;1&amp;8\\
1&amp;1&amp;0&amp;5\end{array}\right]\]
The reduced row echelon form of the augmented matrix.
\[\left[\begin{array}[]{ccc|c}\boxed{1}&amp;0&amp;1&amp;3\\
0&amp;\boxed{1}&amp;-1&amp;2\\
0&amp;0&amp;0&amp;0\end{array}\right]\]
The last column is not a pivot column. So the system of linear equations is consistent. $r=2$, there are $3-2$ free variables. In fact $D=\{1,2\}$, $F=\{3\}$. $x_{1},x_{2}$ are dependent variables, $x_{3}$ is a free variables.
\begin{align*}
x_1 &amp;= 3-x_3 \\
x_2 &amp;= 2+x_3
\end{align*} </paragraphs>
                    <hr xmlns="http://www.w3.org/1999/xhtml" environment="newcol"/>
                  </newcol>
                </item>
                <item course="Math 1030" chapter="7" chapter_type="" section="3" subsection="" subsubsection="" environment="enumerate" wbtag="item">
                  <paragraphs course="Math 1030" chapter="7" chapter_type="" section="3" subsection="" subsubsection="" environment="enumerate" wbtag="paragraphs"> System of linear equations with $n=3,m=3$.</paragraphs>
                  <newline course="Math 1030" chapter="7" chapter_type="" section="3" subsection="" subsubsection="" environment="enumerate"/>
                  <newcol course="Math 1030" chapter="7" chapter_type="" section="3" subsection="" subsubsection="" environment="newcol" wbtag="newcol">
                    <paragraphs course="Math 1030" chapter="7" chapter_type="" section="3" subsection="" subsubsection="" environment="newcol" wbtag="paragraphs"> \begin{align*}
-7x_1 -6 x_2 - 12x_3 &amp;=-33\\
5x_1  + 5x_2 + 7x_3 &amp;=24\\
x_1 +4x_3 &amp;=5
\end{align*}
Augmented matrix
\[\left[\begin{array}[]{ccc|c}-7&amp;-6&amp;-12&amp;-33\\
5&amp;5&amp;7&amp;24\\
1&amp;0&amp;4&amp;5\end{array}\right]\]
The reduced row echelon form of the augmented matrix.
\[\left[\begin{array}[]{ccc|c}\boxed{1}&amp;0&amp;0&amp;-3\\
0&amp;\boxed{1}&amp;0&amp;5\\
0&amp;0&amp;\boxed{1}&amp;2\end{array}\right]\]
The last column is not a pivot column. So the system of linear equations is consistent. $r=3$, there are $3-3=0$ free variables. So the solution is unique. In fact
In fact
\begin{align*}
x_1 &amp;= -3 \\
x_2 &amp;= 5 \\
x_3 &amp;= 2
\end{align*} </paragraphs>
                    <hr xmlns="http://www.w3.org/1999/xhtml" environment="newcol"/>
                  </newcol>
                </item>
                <item course="Math 1030" chapter="7" chapter_type="" section="3" subsection="" subsubsection="" environment="enumerate" wbtag="item">
                  <paragraphs course="Math 1030" chapter="7" chapter_type="" section="3" subsection="" subsubsection="" environment="enumerate" wbtag="paragraphs"> System of linear equations with $n=2$, $m=5$.</paragraphs>
                  <newline course="Math 1030" chapter="7" chapter_type="" section="3" subsection="" subsubsection="" environment="enumerate"/>
                  <newcol course="Math 1030" chapter="7" chapter_type="" section="3" subsection="" subsubsection="" environment="newcol" wbtag="newcol">
                    <paragraphs course="Math 1030" chapter="7" chapter_type="" section="3" subsection="" subsubsection="" environment="newcol" wbtag="paragraphs"> \begin{align*}
2x_1  + 3x_2  &amp;= 6 \\
-x_1 + 4x_2  &amp;=  -14 \\
3x_1 +10x_2  &amp;=  -2  \\
3x_1 - x_2  &amp;=  20  \\
6x_1 + 9x_2  &amp;=  18
\end{align*}
Augmented matrix
\[\left[\begin{array}[]{cc|c}2&amp;3&amp;6\\
-1&amp;4&amp;-14\\
3&amp;10&amp;-2\\
3&amp;-1&amp;20\\
6&amp;9&amp;18\end{array}\right]\]
The reduced row echelon form of the augmented matrix.
\[\left[\begin{array}[]{cc|c}\boxed{1}&amp;0&amp;6\\
0&amp;\boxed{1}&amp;-2\\
0&amp;0&amp;0\\
0&amp;0&amp;0\\
0&amp;0&amp;0\end{array}\right]\]
The last column is not a pivot column. So the system of linear equations is consistent. $r = 2$, there are $2-2=0$ free variables. So the solution is unique. In fact
\[\displaystyle x_{1}=6\]
\[\displaystyle x_{2}=-2\] </paragraphs>
                    <hr xmlns="http://www.w3.org/1999/xhtml" environment="newcol"/>
                  </newcol>
                </item>
                <item course="Math 1030" chapter="7" chapter_type="" section="3" subsection="" subsubsection="" environment="enumerate" wbtag="item">
                  <paragraphs course="Math 1030" chapter="7" chapter_type="" section="3" subsection="" subsubsection="" environment="enumerate" wbtag="paragraphs"> System of linear equations with $n=4,m=3$.</paragraphs>
                  <newline course="Math 1030" chapter="7" chapter_type="" section="3" subsection="" subsubsection="" environment="enumerate"/>
                  <newcol course="Math 1030" chapter="7" chapter_type="" section="3" subsection="" subsubsection="" environment="newcol" wbtag="newcol">
                    <paragraphs course="Math 1030" chapter="7" chapter_type="" section="3" subsection="" subsubsection="" environment="newcol" wbtag="paragraphs"> \begin{align*}
2x_1  + x_2 + 7x_3 - 7x_4 &amp;= 2 \\
-3x_1 + 4x_2 -5x_3 - 6x_4 &amp;=  3 \\
x_1 +x_2 + 4x_3 - 5x_4 &amp;=  2
\end{align*}
Augmented matrix
\[\left[\begin{array}[]{cccc|c}2&amp;1&amp;7&amp;-7&amp;2\\
-3&amp;4&amp;-5&amp;-6&amp;3\\
1&amp;1&amp;4&amp;-5&amp;2\end{array}\right]\]
The reduced row echelon form of the augmented matrix.
\[\left[\begin{array}[]{cccc|c}\boxed{1}&amp;0&amp;3&amp;-2&amp;0\\
0&amp;\boxed{1}&amp;1&amp;-3&amp;0\\
0&amp;0&amp;0&amp;0&amp;\boxed{1}\end{array}\right]\]
The last column is a pivot column. Hence the system of linear equations is inconsistent. It has no solution. </paragraphs>
                    <hr xmlns="http://www.w3.org/1999/xhtml" environment="newcol"/>
                  </newcol>
                </item>
              </enumerate>
            </statement>
          </slide>
          <slide environment="" chapter_type="Chapter" wbtag="slide" canon_num="13" id="s13" slide="13" course="Math 1030" chapter="7" section="3" subsection="" subsubsection="" chapter_title="Types of Solution Sets" section_title="Free variables">
            <keywords slide="13" environ="slide" chapter="7" course="Math 1030">
              <keyword chapter="7" slide="13">Possible Solution Sets for Linear Systems</keyword>
              <keyword chapter="7" slide="13">Consistent More Variables than Equations Infinite solutions</keyword>
            </keywords>
            <statement environment="statement" chapter_type="Chapter" type="Theorem" wbtag="thm" num="12" title="Possible Solution Sets for Linear Systems" md5="0fa316e7afdda3206208fc1f3f8a217d" course="Math 1030" chapter="7" slide="13" item="7.12">
              <title environment="title" chapter_type="Chapter" wbtag="statement" scope="" course="Math 1030" chapter="7" section="3" subsection="" subsubsection="" serial="" slide="13">Possible Solution Sets for Linear Systems</title>
              <label wbtag="label" name="PSSLS" type="Theorem"/>
              <paragraphs course="Math 1030" chapter="7" chapter_type="" section="3" subsection="" subsubsection="" environment="statement" wbtag="paragraphs"> A system of linear equations has no solutions, a unique solution or infinitely many solutions. </paragraphs>
            </statement>
            <substatement environment="substatement" chapter_type="Chapter" type="Proof" wbtag="proof" md5="7082059ea8b320564cfdfe549d01df06" course="Math 1030" chapter="7" slide="13" of="0fa316e7afdda3206208fc1f3f8a217d" of-src-course="Math 1030" of-src-chapter="7" of-src-slide="13" of-type="Theorem" of-item="7.12" of-src-filename="lec7.xml" ofmd5="0fa316e7afdda3206208fc1f3f8a217d" of-serial="">
              <of-title>Possible Solution Sets for Linear Systems</of-title>
              <newcol course="Math 1030" chapter="7" chapter_type="" section="3" subsection="" subsubsection="" environment="newcol" wbtag="newcol">
                <paragraphs course="Math 1030" chapter="7" chapter_type="" section="3" subsection="" subsubsection="" environment="newcol" wbtag="paragraphs"> If the system is inconsistent, that it has no solutions.Suppose the system is consistent. If it has $0$ free variable, it has a unique solution.
If it has $\geq 1$ free variables, it has infinite many solutions. </paragraphs>
                <qed course="Math 1030" chapter="7" chapter_type="" section="3" subsection="" subsubsection="" environment="newcol"/>
              </newcol>
            </substatement>
            <statement environment="statement" chapter_type="Chapter" type="Theorem" wbtag="thm" num="13" title="Consistent More Variables than Equations Infinite solutions" md5="74de9d7ca3852f51b1be98a3f36fb8c9" course="Math 1030" chapter="7" slide="13" item="7.13">
              <title environment="title" chapter_type="Chapter" wbtag="statement" scope="" course="Math 1030" chapter="7" section="3" subsection="" subsubsection="" serial="" slide="13">Consistent, More Variables than Equations, Infinite solutions</title>
              <label wbtag="label" name="CMVEI" type="Theorem"/>
              <newcol course="Math 1030" chapter="7" chapter_type="" section="3" subsection="" subsubsection="" environment="newcol" wbtag="newcol">
                <paragraphs course="Math 1030" chapter="7" chapter_type="" section="3" subsection="" subsubsection="" environment="newcol" wbtag="paragraphs"> Suppose a consistent system of linear equations has $m$ equations in $n$ variables. If $n&gt;m$, then the system has infinitely many solutions. </paragraphs>
              </newcol>
            </statement>
            <substatement environment="substatement" chapter_type="Chapter" type="Proof" wbtag="proof" md5="9362b7d86f68b765ca5ac03ed4668511" course="Math 1030" chapter="7" slide="13" of="74de9d7ca3852f51b1be98a3f36fb8c9" of-src-course="Math 1030" of-src-chapter="7" of-src-slide="13" of-type="Theorem" of-item="7.13" of-src-filename="lec7.xml" ofmd5="74de9d7ca3852f51b1be98a3f36fb8c9" of-serial="">
              <of-title>Consistent, More Variables than Equations, Infinite solutions</of-title>
              <newcol course="Math 1030" chapter="7" chapter_type="" section="3" subsection="" subsubsection="" environment="newcol" wbtag="newcol">
                <paragraphs course="Math 1030" chapter="7" chapter_type="" section="3" subsection="" subsubsection="" environment="newcol" wbtag="paragraphs"> Suppose that the augmented matrix of the system of equations is row-equivalent to $B$, a matrix in reduced row-echelon form with $r$ nonzero rows.
Because $B$ has $m$ rows in total, the number of nonzero rows is less than or equal to $m$. In other words, $r\leq m$.
Follow this with the hypothesis that $n&gt;m$ and we find that the system has a solution set described by at least one free variable because
\[n-r\geq n-m&gt;0.\]
A consistent system with free variables will have an infinite number of solutions, as given by Theorem        </paragraphs>
                <ref environment="newcol" chapter_type="" label="CSRN" wbtag="ref" course="Math 1030" chapter="7" slide="13" src-course="Math 1030" src-chapter="7" src-slide="10" type="Theorem" item="7.9" src-filename="lec7.xml" md5="d2c8db147df80ef12421ed89e4fb12e5" class="lcref" serial="">
                  <title>Consistent Systems, $r$ and $n$</title>
                </ref>
                <paragraphs course="Math 1030" chapter="7" chapter_type="" section="3" subsection="" subsubsection="" environment="newcol" wbtag="paragraphs">. </paragraphs>
                <qed course="Math 1030" chapter="7" chapter_type="" section="3" subsection="" subsubsection="" environment="newcol"/>
              </newcol>
            </substatement>
          </slide>
          <slide environment="" chapter_type="Chapter" wbtag="slide" canon_num="14" id="s14" slide="14" course="Math 1030" chapter="7" section="3" subsection="" subsubsection="" chapter_title="Types of Solution Sets" section_title="Free variables">
            <keywords slide="14" environ="slide" chapter="7" course="Math 1030">
              <keyword chapter="7" slide="14">Steps of Solving a System of Linear Equations.</keyword>
            </keywords>
            <paragraphs course="Math 1030" chapter="7" chapter_type="" section="3" subsection="" subsubsection="" environment="" wbtag="paragraphs"> These theorems give us the procedures and implications that allow us to completely solve any system of linear equations. The main computational tool is using row operations to convert an augmented matrix into reduced row-echelon form. Here is a broad outline of how we would instruct a computer to solve a system of linear equations. </paragraphs>
            <h5 xmlns="http://www.w3.org/1999/xhtml" environment="">
              <paragraphs xmlns="http://www.math.cuhk.edu.hk/~pschan/cranach" course="Math 1030" chapter="7" chapter_type="" section="3" subsection="" subsubsection="" environment="" wbtag="paragraphs">Steps of Solving a System of Linear Equations.</paragraphs>
            </h5>
            <enumerate course="Math 1030" chapter="7" chapter_type="" section="3" subsection="" subsubsection="" environment="enumerate" wbtag="enumerate">
              <item course="Math 1030" chapter="7" chapter_type="" section="3" subsection="" subsubsection="" environment="enumerate" wbtag="item">
                <newcol course="Math 1030" chapter="7" chapter_type="" section="3" subsection="" subsubsection="" environment="newcol" wbtag="newcol">
                  <paragraphs course="Math 1030" chapter="7" chapter_type="" section="3" subsection="" subsubsection="" environment="newcol" wbtag="paragraphs"> Represent a system of linear equations in $n$ variables by an augmented matrix. </paragraphs>
                </newcol>
              </item>
              <item course="Math 1030" chapter="7" chapter_type="" section="3" subsection="" subsubsection="" environment="enumerate" wbtag="item">
                <newcol course="Math 1030" chapter="7" chapter_type="" section="3" subsection="" subsubsection="" environment="newcol" wbtag="newcol">
                  <paragraphs course="Math 1030" chapter="7" chapter_type="" section="3" subsection="" subsubsection="" environment="newcol" wbtag="paragraphs"> Convert the matrix to a row-equivalent matrix in reduced row-echelon form using the procedure given in lecture 3 Theorem 2.
Identify the location of the pivot columns, and the rank $r$. </paragraphs>
                </newcol>
              </item>
              <item course="Math 1030" chapter="7" chapter_type="" section="3" subsection="" subsubsection="" environment="enumerate" wbtag="item">
                <newcol course="Math 1030" chapter="7" chapter_type="" section="3" subsection="" subsubsection="" environment="newcol" wbtag="newcol">
                  <paragraphs course="Math 1030" chapter="7" chapter_type="" section="3" subsection="" subsubsection="" environment="newcol" wbtag="paragraphs"> If column $n+1$ is a pivot column, then the system is inconsistent. </paragraphs>
                </newcol>
              </item>
              <item course="Math 1030" chapter="7" chapter_type="" section="3" subsection="" subsubsection="" environment="enumerate" wbtag="item">
                <newcol course="Math 1030" chapter="7" chapter_type="" section="3" subsection="" subsubsection="" environment="newcol" wbtag="newcol">
                  <paragraphs course="Math 1030" chapter="7" chapter_type="" section="3" subsection="" subsubsection="" environment="newcol" wbtag="paragraphs"> If column $n+1$ is not a pivot column, there are two possibilities: </paragraphs>
                  <enumerate course="Math 1030" chapter="7" chapter_type="" section="3" subsection="" subsubsection="" environment="enumerate" wbtag="enumerate">
                    <item course="Math 1030" chapter="7" chapter_type="" section="3" subsection="" subsubsection="" environment="enumerate" wbtag="item">
                      <paragraphs course="Math 1030" chapter="7" chapter_type="" section="3" subsection="" subsubsection="" environment="enumerate" wbtag="paragraphs"> $r=n$ and the solution is unique. It can be read off directly from the entries in rows 1 through $n$ of column $n+1$. </paragraphs>
                    </item>
                    <item course="Math 1030" chapter="7" chapter_type="" section="3" subsection="" subsubsection="" environment="enumerate" wbtag="item">
                      <paragraphs course="Math 1030" chapter="7" chapter_type="" section="3" subsection="" subsubsection="" environment="enumerate" wbtag="paragraphs"> $r &lt; n$ and there are infinitely many solutions. we can describe the solution sets by the free variables. </paragraphs>
                    </item>
                  </enumerate>
                </newcol>
              </item>
            </enumerate>
          </slide>
        </slides>
      </section>
    </chapter>
  </course>
</document>
